{
  "id": 1782715747359,
  "title": "מתוך 86 מינויים בכירים בשירות הציבורי בשנה האחרונה - 7 בלבד היו של נשים",
  "image": "https://ynet-pic1.yit.co.il/picserver6/crop_images/2020/03/05/H1QmwaAE8/H1QmwaAE8_33_90_934_526_0_medium.jpg",
  "category": "שוק ההון",
  "lang": "he",
  "author": "ynet כלכלה",
  "time": "2026-06-29 04:06",
  "snippet": "דוח חדש מגלה כי רק אחת מכל תשע משרות ציבוריות בכירות מאוישת על ידי אישה. המצב חמור עוד יותר כשמדובר בצמרת מערכת הביטחון ומשרות ראשי ערים או מועצות מקומיות, שם שיעור הנשים הוא רק 6%. וגם: ההידרדרות במערכת המשפט",
  "sourceUrl": "https://www.ynet.co.il/economy/article/yokra14815846",
  "content": "<p style=\"padding:12px;background:#f3f4f6;border-radius:8px;font-size:0.9em;color:#6b7280;margin-bottom:16px;\">📰 מקור: <a href=\"https://www.ynet.co.il/economy/article/yokra14815846\" target=\"_blank\" rel=\"noopener\">ynet כלכלה</a></p><p>דוח חדש מגלה כי רק אחת מכל תשע משרות ציבוריות בכירות מאוישת על ידי אישה. המצב חמור עוד יותר כשמדובר בצמרת מערכת הביטחון ומשרות ראשי ערים או מועצות מקומיות, שם שיעור הנשים הוא רק 6%. וגם: ההידרדרות במערכת המשפט</p>"
}