{
  "id": 1783404590389,
  "title": "משקפי ארמאני ומייקל קורס וחולצות טומי: המוצרים החדשים בסופרמרקטים",
  "image": "https://ynet-pic1.yit.co.il/picserver6/crop_images/2026/07/06/S1cimkFmMx/S1cimkFmMx_0_569_945_532_0_medium.jpg",
  "category": "שוק ההון",
  "lang": "he",
  "author": "ynet כלכלה",
  "time": "2026-07-07 03:59",
  "snippet": "אושר עד החלה למכור בזול משקפי שמש של מותגים בכל הסניפים, רמי לוי מוכר כובעי מצחייה של נייקי ו-ויקטורי חולצות טומי הילפיגר ונעלי ניו באלאנס בחלק מסניפיה",
  "sourceUrl": "https://www.ynet.co.il/economy/article/rkvyc0oxgg",
  "content": "<p style=\"padding:12px;background:#f3f4f6;border-radius:8px;font-size:0.9em;color:#6b7280;margin-bottom:16px;\">📰 מקור: <a href=\"https://www.ynet.co.il/economy/article/rkvyc0oxgg\" target=\"_blank\" rel=\"noopener\">ynet כלכלה</a></p><p>אושר עד החלה למכור בזול משקפי שמש של מותגים בכל הסניפים, רמי לוי מוכר כובעי מצחייה של נייקי ו-ויקטורי חולצות טומי הילפיגר ונעלי ניו באלאנס בחלק מסניפיה</p>"
}