{
  "id": 1784611302460,
  "title": "ממשיכים לשלם ארנונה על בית הרוס: הדיירים שנשכחו ברחוב פינסקר",
  "image": "https://ynet-pic1.yit.co.il/picserver6/crop_images/2026/07/20/yk14837721/yk14837721_0_410_2788_1569_0_medium.jpg",
  "category": "שוק ההון",
  "lang": "he",
  "author": "ynet כלכלה",
  "time": "2026-07-21 04:49",
  "snippet": "יותר משנה אחרי שטיל איראני פגע ברחוב פינסקר בתל אביב, שני הבניינים עדיין עומדים הרוסים. בעלת נכס: \"נפל לי טיל על הבית. אני לא צריכה לשלם ארנונה על זה\". העירייה: \"הנכס מיצה את תקופת הפטור המלאה הקבועה בדין\"",
  "sourceUrl": "https://www.ynet.co.il/economy/article/hyc4ku34fl",
  "content": "<p style=\"padding:12px;background:#f3f4f6;border-radius:8px;font-size:0.9em;color:#6b7280;margin-bottom:16px;\">📰 מקור: <a href=\"https://www.ynet.co.il/economy/article/hyc4ku34fl\" target=\"_blank\" rel=\"noopener\">ynet כלכלה</a></p><p>יותר משנה אחרי שטיל איראני פגע ברחוב פינסקר בתל אביב, שני הבניינים עדיין עומדים הרוסים. בעלת נכס: \"נפל לי טיל על הבית. אני לא צריכה לשלם ארנונה על זה\". העירייה: \"הנכס מיצה את תקופת הפטור המלאה הקבועה בדין\"</p>"
}