{
  "id": 1784350170752,
  "title": "המדינה מחלקת 260 מיליון שקל לאזרחים: כך תדעו אם אתם זכאים",
  "image": "https://ynet-pic1.yit.co.il/picserver6/crop_images/2020/03/08/9833322/9833322_0_0_8688_4887_0_medium.jpg",
  "category": "שוק ההון",
  "lang": "he",
  "author": "ynet כלכלה",
  "time": "2026-07-17 06:21",
  "snippet": "רשות המיסים מעבירה את הפעימה הראשונה של מענק העבודה ל-2025 ל-130 אלף זכאים. הזכאות נקבעת לפי גיל, הורות ורמת הכנסה, והבקשה למענק - שיכול להגיע לאלפי שקלים בשנה - ניתנת להגשה מקוונת באתר הרשות",
  "sourceUrl": "https://www.ynet.co.il/economy/article/rkfapx8efg",
  "content": "<p style=\"padding:12px;background:#f3f4f6;border-radius:8px;font-size:0.9em;color:#6b7280;margin-bottom:16px;\">📰 מקור: <a href=\"https://www.ynet.co.il/economy/article/rkfapx8efg\" target=\"_blank\" rel=\"noopener\">ynet כלכלה</a></p><p>רשות המיסים מעבירה את הפעימה הראשונה של מענק העבודה ל-2025 ל-130 אלף זכאים. הזכאות נקבעת לפי גיל, הורות ורמת הכנסה, והבקשה למענק - שיכול להגיע לאלפי שקלים בשנה - ניתנת להגשה מקוונת באתר הרשות</p>"
}